{"customerId": 1, "longitudeCustomer": 1, "latitudeCustomer" : 1, "availabilityFrom" : 0, "panelsToInstall" : 10}
{"customerId": 2, "longitudeCustomer": 51, "latitudeCustomer" : 9, "availabilityFrom" : 0, "panelsToInstall" : 10}
{"customerId": 3, "longitudeCustomer": 49, "latitudeCustomer" : 9, "availabilityFrom" : 0, "panelsToInstall" : 10}
{"customerId": 4, "longitudeCustomer": 50, "latitudeCustomer" : 9, "availabilityFrom" : 0, "panelsToInstall" : 10}
{"customerId": 5, "longitudeCustomer": 51.5200, "latitudeCustomer" : 13.4050, "availabilityFrom" : 0, "panelsToInstall" : 10}
{"customerId": 6, "longitudeCustomer": 1, "latitudeCustomer" : 1, "availabilityFrom" : 0, "panelsToInstall" : 10}
{"customerId": 7, "longitudeCustomer": 1, "latitudeCustomer" : 1, "availabilityFrom" : 0, "panelsToInstall" : 10}
{"customerId": 8, "longitudeCustomer": 1, "latitudeCustomer" : 1, "availabilityFrom" : 0, "panelsToInstall" : 10}
{"customerId": 9, "longitudeCustomer": 1, "latitudeCustomer" : 1, "availabilityFrom" : 0, "panelsToInstall" : 10}
{"customerId": 10, "longitudeCustomer": 1, "latitudeCustomer" : 1, "availabilityFrom" : 0, "panelsToInstall" : 10}
{"customerId": 11, "longitudeCustomer": 1, "latitudeCustomer" : 1, "availabilityFrom" : 0, "panelsToInstall" : 10}
{"customerId": 12, "longitudeCustomer": 1, "latitudeCustomer" : 1, "availabilityFrom" : 0, "panelsToInstall" : 10}
{"customerId": 13, "longitudeCustomer": 1, "latitudeCustomer" : 1, "availabilityFrom" : 0, "panelsToInstall" : 10}
{"customerId": 14, "longitudeCustomer": 1, "latitudeCustomer" : 1, "availabilityFrom" : 0, "panelsToInstall" : 10}
{"customerId": 15, "longitudeCustomer": 1, "latitudeCustomer" : 1, "availabilityFrom" : 0, "panelsToInstall" : 10}
